{
  "count": 18239,
  "results": [
    {
      "id": "c46b2fd1-d7ec-43d8-a715-c0c4a6dbdfde",
      "brand": "Nike",
      "colorway": "Black/University Red/White",
      "gender": "child",
      "name": "Black University Red (GS)",
      "releaseDate": "2021-07-16",
      "retailPrice": 65,
      "shoe": "Court Borough Low 2",
      "styleId": "BQ5448-007",
      "title": "Court Borough Low 2 Black University Red (GS)",
      "year": 2021,
      "media": {
        "imageUrl": "https://images.stockx.com/images/Nike-Court-Borough-Low-2-Black-University-Red-GS.jpg?fit=fill&bg=FFFFFF&w=700&h=500&auto=format,compress&trim=color&q=90&dpr=2&updated_at=1614886339",
        "smallImageUrl": "https://images.stockx.com/images/Nike-Court-Borough-Low-2-Black-University-Red-GS.jpg?fit=fill&bg=FFFFFF&w=300&h=214&auto=format,compress&trim=color&q=90&dpr=2&updated_at=1614886339",
        "thumbUrl": "https://images.stockx.com/images/Nike-Court-Borough-Low-2-Black-University-Red-GS.jpg?fit=fill&bg=FFFFFF&w=140&h=100&auto=format,compress&trim=color&q=90&dpr=2&updated_at=1614886339"
      }
    },
    {
      "id": "26cf5cd7-99b9-43c8-b2d1-9b4d494bd07c",
      "brand": "Nike",
      "colorway": "White/Game Royal",
      "gender": "toddler",
      "name": "Game Royal (TD)",
      "releaseDate": "2021-06-11",
      "retailPrice": 0,
      "shoe": "Nike Dunk High",
      "styleId": "DD2314-102",
      "title": "Nike Dunk High Game Royal (TD)",
      "year": 2021,
      "media": {
        "imageUrl": null,
        "smallImageUrl": null,
        "thumbUrl": null
      }
    },
    {
      "id": "333ea741-ee8b-4d4c-b278-48b673d747e8",
      "brand": "Nike",
      "colorway": "White/Game Royal",
      "gender": "men",
      "name": "Game Royal",
      "releaseDate": "2021-06-11",
      "retailPrice": 120,
      "shoe": "Nike Dunk High",
      "styleId": "DD1399-102",
      "title": "Nike Dunk High Game Royal",
      "year": 2021,
      "media": {
        "imageUrl": "https://images.stockx.com/images/Nike-Dunk-High-Game-Royal.jpg?fit=fill&bg=FFFFFF&w=700&h=500&auto=format,compress&trim=color&q=90&dpr=2&updated_at=1613038501",
        "smallImageUrl": "https://images.stockx.com/images/Nike-Dunk-High-Game-Royal.jpg?fit=fill&bg=FFFFFF&w=300&h=214&auto=format,compress&trim=color&q=90&dpr=2&updated_at=1613038501",
        "thumbUrl": "https://images.stockx.com/images/Nike-Dunk-High-Game-Royal.jpg?fit=fill&bg=FFFFFF&w=140&h=100&auto=format,compress&trim=color&q=90&dpr=2&updated_at=1613038501"
      }
    },
    {
      "id": "4be1fd28-8ed7-40f6-ab7d-9df757695438",
      "brand": "Nike",
      "colorway": "White/Game Royal",
      "gender": "child",
      "name": "Game Royal (GS)",
      "releaseDate": "2021-06-11",
      "retailPrice": 0,
      "shoe": "Nike Dunk High",
      "styleId": "DB2179-102",
      "title": "Nike Dunk High Game Royal (GS)",
      "year": 2021,
      "media": {
        "imageUrl": null,
        "smallImageUrl": null,
        "thumbUrl": null
      }
    },
    {
      "id": "82d4c6fa-aa06-4540-8e07-99b7d2534ab4",
      "brand": "Nike",
      "colorway": "Black/Purple/Varsity Yellow",
      "gender": "men",
      "name": "Lakers",
      "releaseDate": "2021-05-28",
      "retailPrice": 110,
      "shoe": "Nike Dunk High EMB",
      "styleId": "DH0642-001",
      "title": "Nike Dunk High EMB Lakers",
      "year": 2021,
      "media": {
        "imageUrl": "https://images.stockx.com/images/Nike-Air-Force-1-High-EMB-Lakers.jpg?fit=fill&bg=FFFFFF&w=700&h=500&auto=format,compress&trim=color&q=90&dpr=2&updated_at=1619030796",
        "smallImageUrl": "https://images.stockx.com/images/Nike-Air-Force-1-High-EMB-Lakers.jpg?fit=fill&bg=FFFFFF&w=300&h=214&auto=format,compress&trim=color&q=90&dpr=2&updated_at=1619030796",
        "thumbUrl": "https://images.stockx.com/images/Nike-Air-Force-1-High-EMB-Lakers.jpg?fit=fill&bg=FFFFFF&w=140&h=100&auto=format,compress&trim=color&q=90&dpr=2&updated_at=1619030796"
      }
    },
    {
      "id": "2647c9d0-6e0c-4e95-84f7-bb85fc5c71e9",
      "brand": "Nike",
      "colorway": "Black/Multi",
      "gender": "men",
      "name": "TV Signal",
      "releaseDate": "2021-05-15",
      "retailPrice": 0,
      "shoe": "Nike SB Dunk High",
      "styleId": "CZ2253-100",
      "title": "Nike SB Dunk High TV Signal",
      "year": 2021,
      "media": {
        "imageUrl": "https://images.stockx.com/images/Nike-SB-Dunk-High-TV-Signal.jpg?fit=fill&bg=FFFFFF&w=700&h=500&auto=format,compress&trim=color&q=90&dpr=2&updated_at=1619127303",
        "smallImageUrl": "https://images.stockx.com/images/Nike-SB-Dunk-High-TV-Signal.jpg?fit=fill&bg=FFFFFF&w=300&h=214&auto=format,compress&trim=color&q=90&dpr=2&updated_at=1619127303",
        "thumbUrl": "https://images.stockx.com/images/Nike-SB-Dunk-High-TV-Signal.jpg?fit=fill&bg=FFFFFF&w=140&h=100&auto=format,compress&trim=color&q=90&dpr=2&updated_at=1619127303"
      }
    },
    {
      "id": "ef22b2f3-8768-4971-81b3-ed727bc643b7",
      "brand": "Nike",
      "colorway": "Black/White-Ghost",
      "gender": "men",
      "name": "Ghost",
      "releaseDate": "2021-05-14",
      "retailPrice": 150,
      "shoe": "Nike Cosmic Unity",
      "styleId": "DA6725-003",
      "title": "Nike Cosmic Unity Ghost",
      "year": 2021,
      "media": {
        "imageUrl": "https://images.stockx.com/images/Nike-Cosmic-Unity-Ghost.jpg?fit=fill&bg=FFFFFF&w=700&h=500&auto=format,compress&trim=color&q=90&dpr=2&updated_at=1619127297",
        "smallImageUrl": "https://images.stockx.com/images/Nike-Cosmic-Unity-Ghost.jpg?fit=fill&bg=FFFFFF&w=300&h=214&auto=format,compress&trim=color&q=90&dpr=2&updated_at=1619127297",
        "thumbUrl": "https://images.stockx.com/images/Nike-Cosmic-Unity-Ghost.jpg?fit=fill&bg=FFFFFF&w=140&h=100&auto=format,compress&trim=color&q=90&dpr=2&updated_at=1619127297"
      }
    },
    {
      "id": "4ec6b400-7e3a-45ed-b397-6584f625340a",
      "brand": "Nike",
      "colorway": "White/Team Green-White",
      "gender": "men",
      "name": "Team Green",
      "releaseDate": "2021-05-13",
      "retailPrice": 100,
      "shoe": "Nike Dunk Low",
      "styleId": "",
      "title": "Nike Dunk Low Team Green",
      "year": 2021,
      "media": {
        "imageUrl": "https://images.stockx.com/images/Nike-Dunk-Low-Team-Green.jpg?fit=fill&bg=FFFFFF&w=700&h=500&auto=format,compress&trim=color&q=90&dpr=2&updated_at=1617577383",
        "smallImageUrl": "https://images.stockx.com/images/Nike-Dunk-Low-Team-Green.jpg?fit=fill&bg=FFFFFF&w=300&h=214&auto=format,compress&trim=color&q=90&dpr=2&updated_at=1617577383",
        "thumbUrl": "https://images.stockx.com/images/Nike-Dunk-Low-Team-Green.jpg?fit=fill&bg=FFFFFF&w=140&h=100&auto=format,compress&trim=color&q=90&dpr=2&updated_at=1617577383"
      }
    },
    {
      "id": "b063f21b-b98b-4dda-b076-c958cc724b09",
      "brand": "Nike",
      "colorway": "University Gold/Navy/White",
      "gender": "men",
      "name": "Michigan",
      "releaseDate": "2021-05-13",
      "retailPrice": 100,
      "shoe": "Nike Dunk Low",
      "styleId": "DD1391-700",
      "title": "Nike Dunk Low Michigan",
      "year": 2021,
      "media": {
        "imageUrl": "https://images.stockx.com/images/Nike-Dunk-Low-Michigan-Product.jpg?fit=fill&bg=FFFFFF&w=700&h=500&auto=format,compress&trim=color&q=90&dpr=2&updated_at=1619204735",
        "smallImageUrl": "https://images.stockx.com/images/Nike-Dunk-Low-Michigan-Product.jpg?fit=fill&bg=FFFFFF&w=300&h=214&auto=format,compress&trim=color&q=90&dpr=2&updated_at=1619204735",
        "thumbUrl": "https://images.stockx.com/images/Nike-Dunk-Low-Michigan-Product.jpg?fit=fill&bg=FFFFFF&w=140&h=100&auto=format,compress&trim=color&q=90&dpr=2&updated_at=1619204735"
      }
    },
    {
      "id": "6e9f0825-fa55-48a6-b0be-64d5fd14a787",
      "brand": "Nike",
      "colorway": "Pale Ivory/Chlorine Blue-Black",
      "gender": "men",
      "name": "Pale Ivory",
      "releaseDate": "2021-05-01",
      "retailPrice": 130,
      "shoe": "Nike Kyrie 7",
      "styleId": "CZ0141-100",
      "title": "Nike Kyrie 7 Pale Ivory",
      "year": 2021,
      "media": {
        "imageUrl": "https://images.stockx.com/images/Nike-Kyrie-7-Pale-Ivory.jpg?fit=fill&bg=FFFFFF&w=700&h=500&auto=format,compress&trim=color&q=90&dpr=2&updated_at=1619127355",
        "smallImageUrl": "https://images.stockx.com/images/Nike-Kyrie-7-Pale-Ivory.jpg?fit=fill&bg=FFFFFF&w=300&h=214&auto=format,compress&trim=color&q=90&dpr=2&updated_at=1619127355",
        "thumbUrl": "https://images.stockx.com/images/Nike-Kyrie-7-Pale-Ivory.jpg?fit=fill&bg=FFFFFF&w=140&h=100&auto=format,compress&trim=color&q=90&dpr=2&updated_at=1619127355"
      }
    }
  ]
}